setup.py
tdlc/__init__.py
tdlc/exceptions.py
tdlc/engines/__init__.py
tdlc/engines/cloudapi.py
tdlc/engines/controllers.py
tdlc/engines/qclient.py
tdlc/engines/sessions.py
tdlc/engines/commands/__init__.py
tdlc/engines/commands/command.py
tdlc/engines/commands/pandas2spark.py
tdlc/engines/commands/sqlcommand.py
tdlc/engines/commands/storecommand.py
tdlc/engines/commands/string2spark.py
tdlc/engines/commands/var2spark.py
tdlc/kernels/__init__.py
tdlc/kernels/kernelbase.py
tdlc/kernels/kernelmagics.py
tdlc/kernels/dlcpysparkkernel/__init__.py
tdlc/kernels/dlcpysparkkernel/pysparkkernel.py
tdlc/kernels/dlcsparkkernel/__init__.py
tdlc/kernels/dlcsparkkernel/sparkkernel.py
tdlc/magics/__init__.py
tdlc/magics/basemagics.py
tdlc/magics/remotemagics.py
tdlc/tencentcloud/__init__.py
tdlc/tencentcloud/common/__init__.py
tdlc/tencentcloud/common/abstract_client.py
tdlc/tencentcloud/common/abstract_model.py
tdlc/tencentcloud/common/common_client.py
tdlc/tencentcloud/common/credential.py
tdlc/tencentcloud/common/sign.py
tdlc/tencentcloud/common/exception/__init__.py
tdlc/tencentcloud/common/exception/tencent_cloud_sdk_exception.py
tdlc/tencentcloud/common/http/__init__.py
tdlc/tencentcloud/common/http/request.py
tdlc/tencentcloud/common/profile/__init__.py
tdlc/tencentcloud/common/profile/client_profile.py
tdlc/tencentcloud/common/profile/http_profile.py
tdlc/tencentcloud/dlc/__init__.py
tdlc/tencentcloud/dlc/v20210125/__init__.py
tdlc/tencentcloud/dlc/v20210125/dlc_client.py
tdlc/tencentcloud/dlc/v20210125/errorcodes.py
tdlc/tencentcloud/dlc/v20210125/models.py
tdlc/utils/__init__.py
tdlc/utils/common.py
tdlc/utils/configurations.py
tdlc/utils/constants.py
tdlc/utils/log.py
tdlc/utils/render.py
tdlc/utils/validators.py
tdlc/widgets/__init__.py
tdlc/widgets/configuiwidget.py
tdlc/widgets/createsessionwidget.py
tdlc/widgets/managesessionwidget.py
tencentcloud_dlc_jupyter.egg-info/PKG-INFO
tencentcloud_dlc_jupyter.egg-info/SOURCES.txt
tencentcloud_dlc_jupyter.egg-info/dependency_links.txt
tencentcloud_dlc_jupyter.egg-info/requires.txt
tencentcloud_dlc_jupyter.egg-info/top_level.txt