Metadata-Version: 2.1
Name: tencentcloud-dlc-jupyter
Version: 1.1.1
Summary: Tencentcloud DLC jupyter pulgin. Coding with elastic spark engines in jupyter.
Home-page: UNKNOWN
Author: Tencentcloud DLC Team.
Maintainer-email: valuxzhao@tencent.com
License: Apache License Version 2.0
Platform: any
